devqubit_engine/__init__.py
devqubit_engine/adapters.py
devqubit_engine/config.py
devqubit_engine/py.typed
devqubit_engine/query.py
devqubit_engine/bundle/__init__.py
devqubit_engine/bundle/pack.py
devqubit_engine/bundle/reader.py
devqubit_engine/bundle/replay.py
devqubit_engine/circuit/__init__.py
devqubit_engine/circuit/extractors.py
devqubit_engine/circuit/hashing.py
devqubit_engine/circuit/models.py
devqubit_engine/circuit/registry.py
devqubit_engine/circuit/summary.py
devqubit_engine/cli/__init__.py
devqubit_engine/cli/_utils.py
devqubit_engine/cli/admin.py
devqubit_engine/cli/artifacts.py
devqubit_engine/cli/bundle.py
devqubit_engine/cli/compare.py
devqubit_engine/cli/runs.py
devqubit_engine/compare/__init__.py
devqubit_engine/compare/_formatting.py
devqubit_engine/compare/ci.py
devqubit_engine/compare/context.py
devqubit_engine/compare/diff.py
devqubit_engine/compare/drift.py
devqubit_engine/compare/results.py
devqubit_engine/compare/types.py
devqubit_engine/compare/verdict.py
devqubit_engine/compare/verify.py
devqubit_engine/schema/__init__.py
devqubit_engine/schema/devqubit.envelope.1.0.schema.json
devqubit_engine/schema/devqubit.run.1.0.schema.json
devqubit_engine/schema/validation.py
devqubit_engine/storage/__init__.py
devqubit_engine/storage/errors.py
devqubit_engine/storage/factory.py
devqubit_engine/storage/gc.py
devqubit_engine/storage/types.py
devqubit_engine/storage/artifacts/__init__.py
devqubit_engine/storage/artifacts/counts.py
devqubit_engine/storage/artifacts/io.py
devqubit_engine/storage/artifacts/lookup.py
devqubit_engine/storage/backends/__init__.py
devqubit_engine/storage/backends/local.py
devqubit_engine/storage/backends/remote_gcs.py
devqubit_engine/storage/backends/remote_s3.py
devqubit_engine/tracking/__init__.py
devqubit_engine/tracking/fingerprints.py
devqubit_engine/tracking/record.py
devqubit_engine/tracking/run.py
devqubit_engine/uec/__init__.py
devqubit_engine/uec/errors.py
devqubit_engine/uec/api/__init__.py
devqubit_engine-0.1.10.dist-info/METADATA
devqubit_engine-0.1.10.dist-info/WHEEL
devqubit_engine-0.1.10.dist-info/licenses/LICENSE
devqubit_engine-0.1.10.dist-info/RECORD
