Metadata-Version: 2.4
Name: devqubit-engine
Version: 0.1.10
Summary: Internal core runtime for devqubit
Author: devqubit
License-Expression: Apache-2.0
License-File: LICENSE
Keywords: experiment-tracking,quantum
Classifier: Development Status :: 3 - Alpha
Classifier: License :: OSI Approved :: Apache Software License
Classifier: Operating System :: OS Independent
Classifier: Programming Language :: Python :: 3
Classifier: Programming Language :: Python :: 3 :: Only
Classifier: Programming Language :: Python :: 3.11
Classifier: Programming Language :: Python :: 3.12
Classifier: Programming Language :: Python :: 3.13
Requires-Python: <3.14,>=3.11
Requires-Dist: click<9,>=8.2
Requires-Dist: jsonschema<5,>=4.25.1
Requires-Dist: numpy<3,>=2.2
Requires-Dist: py-ulid>=1.0.3
Provides-Extra: gcs
Requires-Dist: google-cloud-storage>=3.7.0; extra == 'gcs'
Provides-Extra: s3
Requires-Dist: boto3>=1.42.10; extra == 's3'
